{
	"name": "5.0.1",
	"version": "5.0.1",
	"catalog": [],
	"releases": [
		{
			"name": "5.0.1",
			"version": "5.0.1",
			"digest": "sha256:98b2a1a9e5b92097434b1ca433569c4b0333eb60ff154b8a687b764dec999446",
			"released": "2021-08-04T21:48:48.412Z"
		}
	],
	"history": [
		{
			"type": "INITIAL",
			"date": "2026-02-08T12:12:39.989Z",
			"actions": [
				{
					"type": "ADDED",
					"version": "5.0.1",
					"name": "5.0.1",
					"digest": "sha256:98b2a1a9e5b92097434b1ca433569c4b0333eb60ff154b8a687b764dec999446"
				}
			]
		}
	],
	"updated": "2026-02-08T12:12:39.989Z"
}