{
	"name": "7.0.3",
	"version": "7.0.3",
	"catalog": [],
	"releases": [
		{
			"name": "7.0.3",
			"version": "7.0.3",
			"digest": "sha256:e86b32dc3df2a30610dd3eeab15132b67d3ae00f3435a3c72ada21b12dfd6c5e",
			"released": "2023-11-16T05:23:21.021Z"
		},
		{
			"name": "7.0.3-rc1",
			"version": "7.0.3",
			"digest": "sha256:c39cef8b2202a1d182cc101b8af32428b2b627378be68b4a4e73b04792e68dda",
			"released": "2023-10-26T23:43:06.700Z"
		}
	],
	"history": [
		{
			"type": "INITIAL",
			"date": "2026-02-08T12:48:28.503Z",
			"actions": [
				{
					"type": "ADDED",
					"version": "7.0.3",
					"name": "7.0.3",
					"digest": "sha256:e86b32dc3df2a30610dd3eeab15132b67d3ae00f3435a3c72ada21b12dfd6c5e"
				},
				{
					"type": "ADDED",
					"version": "7.0.3",
					"name": "7.0.3-rc1",
					"digest": "sha256:c39cef8b2202a1d182cc101b8af32428b2b627378be68b4a4e73b04792e68dda"
				}
			]
		}
	],
	"updated": "2026-02-08T12:48:28.503Z"
}