{
	"name": "4.2.23",
	"version": "4.2.23",
	"catalog": [],
	"releases": [
		{
			"name": "4.2.23",
			"version": "4.2.23",
			"digest": "sha256:9ebb64b9f450fbbc1b5f05b518f7cab055a6a98d3eabd02e9c94d37a1e7464ac",
			"released": "2023-02-16T02:11:01.224Z"
		},
		{
			"name": "4.2.23-rc1",
			"version": "4.2.23",
			"digest": "sha256:dccdcb121fea5f3439c10c703bf168ee536a12d0917644e0bb3811e3c7ecb3f5",
			"released": "2022-09-27T01:44:01.895Z"
		},
		{
			"name": "4.2.23-rc0",
			"version": "4.2.23",
			"digest": "sha256:5da3c1ebd80d793206806d87c9233324616d0c8d9cf62ae704fcb93d46ad51e2",
			"released": "2022-09-14T19:53:24.639Z"
		}
	],
	"history": [
		{
			"type": "INITIAL",
			"date": "2026-02-08T12:25:23.633Z",
			"actions": [
				{
					"type": "ADDED",
					"version": "4.2.23",
					"name": "4.2.23",
					"digest": "sha256:9ebb64b9f450fbbc1b5f05b518f7cab055a6a98d3eabd02e9c94d37a1e7464ac"
				},
				{
					"type": "ADDED",
					"version": "4.2.23",
					"name": "4.2.23-rc1",
					"digest": "sha256:dccdcb121fea5f3439c10c703bf168ee536a12d0917644e0bb3811e3c7ecb3f5"
				},
				{
					"type": "ADDED",
					"version": "4.2.23",
					"name": "4.2.23-rc0",
					"digest": "sha256:5da3c1ebd80d793206806d87c9233324616d0c8d9cf62ae704fcb93d46ad51e2"
				}
			]
		}
	],
	"updated": "2026-02-08T12:25:23.633Z"
}