{
	"name": "6.0.23",
	"version": "6.0.23",
	"catalog": [],
	"releases": [
		{
			"name": "6.0.23",
			"version": "6.0.23",
			"digest": "sha256:58ae5cc66b484600bf441620c30e8231545bc1f0bb217e73ea8cbd13999c856b",
			"released": "2025-06-03T07:07:36.145Z"
		}
	],
	"history": [
		{
			"type": "INITIAL",
			"date": "2026-02-08T14:54:37.196Z",
			"actions": [
				{
					"type": "ADDED",
					"version": "6.0.23",
					"name": "6.0.23",
					"digest": "sha256:58ae5cc66b484600bf441620c30e8231545bc1f0bb217e73ea8cbd13999c856b"
				}
			]
		}
	],
	"updated": "2026-02-08T14:54:37.196Z"
}