{
	"name": "7.0.29",
	"version": "7.0.29",
	"catalog": [],
	"releases": [
		{
			"name": "7.0.29",
			"version": "7.0.29",
			"digest": "sha256:606f8e029603330411a7dd10b5ffd50eefc297fc80cee89f10a455e496a76ae7",
			"released": "2026-01-28T20:07:56.013Z"
		}
	],
	"history": [
		{
			"type": "INITIAL",
			"date": "2026-02-13T07:34:18.172Z",
			"actions": [
				{
					"type": "ADDED",
					"version": "7.0.29",
					"name": "7.0.29",
					"digest": "sha256:606f8e029603330411a7dd10b5ffd50eefc297fc80cee89f10a455e496a76ae7"
				}
			]
		}
	],
	"updated": "2026-02-13T07:34:18.172Z"
}