{
  "queries": [
    {
      "checksum": "f8e7bdb2daa64b841c517f57ba0996d7628338551ef7f6572a437cbd216b86c7",
      "fingerprint": {
        "field:#1": {
          "$ne": "number:#1"
        }
      },
      "query": {
        "age": {
          "$ne": 8
        }
      }
    },
    {
      "checksum": "658c63a241499cf0f77d6fbf1c6f10566c1b1ae55a888deec1cf6deb7e3cf727",
      "fingerprint": {
        "field:#1": {
          "$ne": {}
        }
      },
      "query": {
        "score": {
          "$ne": {}
        }
      }
    },
    {
      "checksum": "9f185ceb7c8b7e90895f1a318f90b9379f7e0f8466776e5d906a489e000e55e8",
      "fingerprint": {
        "field:#1": {
          "$gt": {}
        }
      },
      "query": {
        "score": {
          "$gt": {}
        }
      }
    },
    {
      "checksum": "8c5a4959f4a6890f5156f711eada276faa1ad6261d2a1e790d0d024fbf6fda97",
      "fingerprint": {
        "field:#1": {
          "$gte": {}
        }
      },
      "query": {
        "score": {
          "$gte": {}
        }
      }
    },
    {
      "checksum": "214e29da82cd364194475a0a42a7f66903c50008728d4d63a424fa3dfa90e3c0",
      "fingerprint": {
        "field:#1": {
          "$lt": {}
        }
      },
      "query": {
        "score": {
          "$lt": {}
        }
      }
    },
    {
      "checksum": "a552fc2d47e6e33604ab01a377072db20bdfb45409971c5bd5c3dfe9fd76a314",
      "fingerprint": {
        "field:#1": {
          "$lte": {}
        }
      },
      "query": {
        "score": {
          "$lte": {}
        }
      }
    },
    {
      "checksum": "b9d6c3e12402722af37bbccbcdcc9c8ef27046daca3f435659b77553a60b6bcb",
      "fingerprint": {
        "field:#1": {
          "$elemMatch": {
            "field:#2": {
              "$ne": [
                "number:#1"
              ]
            }
          }
        }
      },
      "query": {
        "scores": {
          "$elemMatch": {
            "level": {
              "$ne": [
                153
              ]
            }
          }
        }
      }
    },
    {
      "checksum": "04947826eb195e48232a5abaccfe3b1f34d978174915682b94a5cfbb8c6ff041",
      "fingerprint": {
        "field:#1": {
          "$elemMatch": {
            "field:#2": {
              "$not": {
                "$in": [
                  [
                    "number:#1"
                  ]
                ]
              }
            }
          }
        }
      },
      "query": {
        "scores": {
          "$elemMatch": {
            "level": {
              "$not": {
                "$in": [
                  [
                    153
                  ]
                ]
              }
            }
          }
        }
      }
    },
    {
      "checksum": "685d0492044795ce6b83d87432fe7eb2900d03570c0ace5665ad6097dca374c3",
      "fingerprint": {
        "field:#1": {
          "$not": {
            "$elemMatch": {
              "field:#2": [
                "number:#1"
              ]
            }
          }
        }
      },
      "query": {
        "scores": {
          "$not": {
            "$elemMatch": {
              "level": [
                153
              ]
            }
          }
        }
      }
    },
    {
      "checksum": "0327b88871f4e901f1ab73e6802261c5ae6ffffa23e25b1dded990ef589e4032",
      "fingerprint": {
        "field:#1": {
          "$not": {
            "$elemMatch": {
              "field:#2": {
                "$in": [
                  [
                    "number:#1"
                  ]
                ]
              }
            }
          }
        }
      },
      "query": {
        "scores": {
          "$not": {
            "$elemMatch": {
              "level": {
                "$in": [
                  [
                    153
                  ]
                ]
              }
            }
          }
        }
      }
    }
  ],
  "variants": [
    {
      "age": {
        "$ne": null
      }
    },
    {
      "age": {
        "$ne": "value"
      }
    },
    {
      "age": {
        "$ne": true
      }
    },
    {
      "scores": {
        "$elemMatch": 42
      }
    },
    {
      "scores": {
        "$elemMatch": {
          "level": {
            "$ne": [
              null
            ]
          }
        }
      }
    },
    {
      "scores": {
        "$elemMatch": {
          "level": {
            "$ne": [
              "value"
            ]
          }
        }
      }
    },
    {
      "scores": {
        "$elemMatch": {
          "level": {
            "$ne": [
              true
            ]
          }
        }
      }
    },
    {
      "scores": {
        "$elemMatch": {
          "level": {
            "$not": {
              "$in": "active"
            }
          }
        }
      }
    },
    {
      "scores": {
        "$elemMatch": {
          "level": {
            "$not": {
              "$in": [
                [
                  null
                ]
              ]
            }
          }
        }
      }
    },
    {
      "scores": {
        "$elemMatch": {
          "level": {
            "$not": {
              "$in": [
                [
                  "value"
                ]
              ]
            }
          }
        }
      }
    },
    {
      "scores": {
        "$elemMatch": {
          "level": {
            "$not": {
              "$in": [
                [
                  true
                ]
              ]
            }
          }
        }
      }
    },
    {
      "scores": {
        "$not": {
          "$elemMatch": 42
        }
      }
    },
    {
      "scores": {
        "$not": {
          "$elemMatch": {
            "level": [
              null
            ]
          }
        }
      }
    },
    {
      "scores": {
        "$not": {
          "$elemMatch": {
            "level": [
              "value"
            ]
          }
        }
      }
    },
    {
      "scores": {
        "$not": {
          "$elemMatch": {
            "level": [
              true
            ]
          }
        }
      }
    },
    {
      "scores": {
        "$not": {
          "$elemMatch": {
            "level": {
              "$in": "active"
            }
          }
        }
      }
    },
    {
      "scores": {
        "$not": {
          "$elemMatch": {
            "level": {
              "$in": [
                [
                  null
                ]
              ]
            }
          }
        }
      }
    },
    {
      "scores": {
        "$not": {
          "$elemMatch": {
            "level": {
              "$in": [
                [
                  "value"
                ]
              ]
            }
          }
        }
      }
    },
    {
      "scores": {
        "$not": {
          "$elemMatch": {
            "level": {
              "$in": [
                [
                  true
                ]
              ]
            }
          }
        }
      }
    }
  ],
  "documents": [
    {
      "_id": 0,
      "age": 7
    },
    {
      "_id": 1,
      "rank": 30,
      "scores": [
        31
      ]
    },
    {
      "_id": 2,
      "rank": 30,
      "scores": [
        [
          153
        ]
      ]
    },
    {
      "_id": 3,
      "rank": 31,
      "scores": [
        34,
        35,
        [
          153
        ]
      ]
    },
    {
      "_id": 4,
      "rank": 31,
      "scores": [
        {
          "level": 153
        }
      ]
    },
    {
      "_id": 5,
      "rank": 32,
      "scores": [
        {
          "level": [
            34,
            [
              153
            ]
          ]
        }
      ]
    },
    {
      "_id": 6,
      "rank": 33,
      "scores": [
        {
          "level": [
            [
              153
            ]
          ]
        }
      ]
    }
  ],
  "indices": [
    {
      "age": 1
    },
    {
      "a.b": 1
    }
  ]
}